pyotgw/__init__.py
pyotgw/commandprocessor.py
pyotgw/connection.py
pyotgw/messageprocessor.py
pyotgw/messages.py
pyotgw/protocol.py
pyotgw/pyotgw.py
pyotgw/status.py
pyotgw/vars.py
pyotgw-2.2.3.dist-info/licenses/LICENSE
pyotgw-2.2.3.dist-info/METADATA
pyotgw-2.2.3.dist-info/WHEEL
pyotgw-2.2.3.dist-info/top_level.txt
pyotgw-2.2.3.dist-info/RECORD
