Metadata-Version: 2.4
Name: pyotgw
Version: 2.2.3
Summary: A library to interface with the opentherm gateway through serial or network connection.
Home-page: https://github.com/mvn23/pyotgw
Author: Milan van Nugteren
Author-email: milan@network23.nl
License: GPLv3+
Keywords: opentherm gateway otgw
Classifier: Development Status :: 5 - Production/Stable
Classifier: Topic :: Software Development :: Libraries
Classifier: License :: OSI Approved :: GNU General Public License v3 or later (GPLv3+)
Requires-Python: >=3.8
License-File: LICENSE
Requires-Dist: pyserial-asyncio-fast
Dynamic: author
Dynamic: author-email
Dynamic: classifier
Dynamic: description
Dynamic: description-content-type
Dynamic: home-page
Dynamic: keywords
Dynamic: license
Dynamic: license-file
Dynamic: requires-dist
Dynamic: requires-python
Dynamic: summary
